[
  {
    "id": "6351967f",
    "eventDate": "18-06-2025",
    "url": "https://www.setlist.fm/setlist/green-day/2025/wiener-stadthalle-halle-d-vienna-austria-6351967f.html",
    "songs": [
      "Forever Now"
    ]
  },
  {
    "id": "4b50476e",
    "eventDate": "17-06-2025",
    "url": "https://www.setlist.fm/setlist/green-day/2025/wiener-stadthalle-halle-d-vienna-austria-4b50476e.html",
    "songs": [
      "Bohemian Rhapsody",
      "Blitzkrieg Bop",
      "Intro Theme",
      "American Idiot",
      "Holiday",
      "Know Your Enemy",
      "Boulevard of Broken Dreams",
      "One Eyed Bastard",
      "86",
      "Longview",
      "Welcome to Paradise",
      "Hitchin' a Ride",
      "Waiting",
      "Brain Stew",
      "St. Jimmy",
      "Dilemma",
      "21 Guns",
      "Minority",
      "Basket Case",
      "When I Come Around",
      "Wake Me Up When September Ends",
      "Jesus of Suburbia",
      "Bobby Sox",
      "Good Riddance (Time of Your Life)"
    ]
  },
  {
    "id": "3b504438",
    "eventDate": "15-06-2025",
    "url": "https://www.setlist.fm/setlist/green-day/2025/visarno-arena-firenze-florence-italy-3b504438.html",
    "songs": [
      "Bohemian Rhapsody",
      "Blitzkrieg Bop",
      "lntro Theme",
      "American Idiot",
      "Holiday",
      "Know Your Enemy",
      "Boulevard of Broken Dreams",
      "One Eyed Bastard",
      "Murder City",
      "Longview",
      "Welcome to Paradise",
      "Hitchin' a Ride",
      "80",
      "Brain Stew",
      "St. Jimmy",
      "Dilemma",
      "21 Guns",
      "Minority",
      "Basket Case",
      "When I Come Around",
      "Wake Me Up When September Ends",
      "Jesus of Suburbia",
      "Bobby Sox",
      "Good Riddance (Time of Your Life)"
    ]
  }
]